Workbook

Sheet Чек-лист
A1: Матемация — что сделать к тестовому запуску
A2: Отмечайте выполненное в столбце «Готово»: выберите ☑ из списка — строка станет серой. Жёлтые столбцы «Готово», «Кто» и «Комментарий» — для заполнения. Фильтры — в строке заголовков.
A3: Готово: | C3: =COUNTIF(B5:B67,"☑")&" из "&COUNTA(E5:E67) | D3: =IFERROR(COUNTIF(B5:B67,"☑")/COUNTA(E5:E67),0)
A4: № | B4: Готово | C4: Этап | D4: Блок | E4: Действие | F4: Как и где | G4: Что передать Claude | H4: Срок | I4: Кто | J4: Комментарий
A5: 1 | B5: ☐ | C5: 1. До выкладки | D5: Безопасность | E5: Перевыпустить токен бота: он был отправлен в чат | F5: @BotFather → /revoke → выбрать @content_mathemation_bot. Новый токен вписать в строку SOCIAL_AGENT_TELEGRAM_BOT_TOKEN в .env и .env.production | G5: Написать «токен заменён» (сам токен не присылать) | H5: сейчас
A6: 2 | B6: ☐ | C6: 1. До выкладки | D6: Безопасность | E6: Секреты — только в файлы .env и .env.production, не в чат | F6: Файлы в корне C:\Dev\Mathemation, в git не попадают | G6: — | H6: постоянно
A7: 3 | B7: ☐ | C7: 1. До выкладки | D7: DeepSeek | E7: Пополнить баланс DeepSeek на $10–20 | F7: platform.deepseek.com → Top up. Сейчас баланс $0 — наставник и контентолог работают на шаблонах | G7: Сообщить «пополнено» — Claude проверит живую подсказку и лимит токенов | H7: до выкладки
A8: 4 | B8: ☐ | C8: 1. До выкладки | D8: DeepSeek | E8: Решить дневной лимит подсказок на ученика | F8: Сейчас 20 в день (AI_MENTOR_DAILY_HINT_LIMIT) | G8: Число | H8: до выкладки
A9: 5 | B9: ☐ | C9: 1. До выкладки | D9: TimeWeb | E9: Завести аккаунт организации или ИП и пополнить баланс | F9: timeweb.cloud — юрлицо/ИП: договор и закрывающие документы, это нужно и для 152-ФЗ | G9: — | H9: до выкладки
A10: 6 | B10: ☐ | C10: 1. До выкладки | D10: TimeWeb | E10: Включить двухфакторный вход в аккаунт TimeWeb | F10: Настройки профиля → безопасность | G10: — | H10: до выкладки
A11: 7 | B11: ☐ | C11: 1. До выкладки | D11: TimeWeb | E11: Все ресурсы создавать в одном регионе: Москва или Санкт-Петербург | F11: Не Нидерланды: данные учеников по 152-ФЗ хранятся в РФ | G11: — | H11: до выкладки
A12: 8 | B12: ☐ | C12: 1. До выкладки | D12: TimeWeb | E12: Создать приватную сеть matemacia-net | F12: Раздел «Сети». В неё — сервер, PostgreSQL и Redis | G12: — | H12: до выкладки
A13: 9 | B13: ☐ | C13: 1. До выкладки | D13: TimeWeb | E13: Создать облачный сервер | F13: Ubuntu 24.04; 2 vCPU, 4 ГБ RAM, 50 ГБ NVMe; публичный IPv4; сеть matemacia-net; доступ по SSH-ключу matemacia-deploy (C:\Users\User\.ssh\matemacia_timeweb.pub), не по паролю | G13: IP сервера | H13: до выкладки
A14: 10 | B14: ☐ | C14: 1. До выкладки | D14: TimeWeb | E14: Настроить firewall и привязать к серверу | F14: Раздел «Firewall»: входящие 22, 80, 443 — разрешить, остальное запретить. Порт 22 — только со своего IP, если он статический | G14: — | H14: до выкладки
A15: 11 | B15: ☐ | C15: 1. До выкладки | D15: TimeWeb | E15: Создать PostgreSQL 16 | F15: «Базы данных» → PostgreSQL 16, минимальная конфигурация, сеть matemacia-net, без публичного IP, база и пользователь matemacia, длинный пароль, автобэкапы включить | G15: Вписать POSTGRES_HOST (приватный адрес) и POSTGRES_PASSWORD в .env.production | H15: до выкладки
A16: 12 | B16: ☐ | C16: 1. До выкладки | D16: TimeWeb | E16: Скачать корневой сертификат базы | F16: Карточка базы → подключение → сертификат. Положить в infra\production\certs\db-root.crt | G16: Сообщить «сертификат положен» | H16: до выкладки
... A67: 63 | B67: ☐ | C67: 5. После теста | D67: Сотрудники | E67: Перевести почты сотрудников на доменные | F67: — | G67: — | H67: после теста

Sheet Сводка
A1: Прогресс по блокам
A3: Блок | B3: Всего | C3: Готово | D3: Осталось | E3: Прогресс
A4: Безопасность | B4: =COUNTIF('Чек-лист'!$D$5:$D$67,A4) | C4: =COUNTIFS('Чек-лист'!$D$5:$D$67,A4,'Чек-лист'!$B$5:$B$67,"☑") | D4: =B4-C4 | E4: =IF(B4=0,0,C4/B4)
A5: DeepSeek | B5: =COUNTIF('Чек-лист'!$D$5:$D$67,A5) | C5: =COUNTIFS('Чек-лист'!$D$5:$D$67,A5,'Чек-лист'!$B$5:$B$67,"☑") | D5: =B5-C5 | E5: =IF(B5=0,0,C5/B5)
A6: TimeWeb | B6: =COUNTIF('Чек-лист'!$D$5:$D$67,A6) | C6: =COUNTIFS('Чек-лист'!$D$5:$D$67,A6,'Чек-лист'!$B$5:$B$67,"☑") | D6: =B6-C6 | E6: =IF(B6=0,0,C6/B6)
A7: Почта | B7: =COUNTIF('Чек-лист'!$D$5:$D$67,A7) | C7: =COUNTIFS('Чек-лист'!$D$5:$D$67,A7,'Чек-лист'!$B$5:$B$67,"☑") | D7: =B7-C7 | E7: =IF(B7=0,0,C7/B7)
A8: Документы | B8: =COUNTIF('Чек-лист'!$D$5:$D$67,A8) | C8: =COUNTIFS('Чек-лист'!$D$5:$D$67,A8,'Чек-лист'!$B$5:$B$67,"☑") | D8: =B8-C8 | E8: =IF(B8=0,0,C8/B8)
A9: Контент | B9: =COUNTIF('Чек-лист'!$D$5:$D$67,A9) | C9: =COUNTIFS('Чек-лист'!$D$5:$D$67,A9,'Чек-лист'!$B$5:$B$67,"☑") | D9: =B9-C9 | E9: =IF(B9=0,0,C9/B9)
A10: Kinescope | B10: =COUNTIF('Чек-лист'!$D$5:$D$67,A10) | C10: =COUNTIFS('Чек-лист'!$D$5:$D$67,A10,'Чек-лист'!$B$5:$B$67,"☑") | D10: =B10-C10 | E10: =IF(B10=0,0,C10/B10)
A11: Сотрудники | B11: =COUNTIF('Чек-лист'!$D$5:$D$67,A11) | C11: =COUNTIFS('Чек-лист'!$D$5:$D$67,A11,'Чек-лист'!$B$5:$B$67,"☑") | D11: =B11-C11 | E11: =IF(B11=0,0,C11/B11)
A12: Контентолог | B12: =COUNTIF('Чек-лист'!$D$5:$D$67,A12) | C12: =COUNTIFS('Чек-лист'!$D$5:$D$67,A12,'Чек-лист'!$B$5:$B$67,"☑") | D12: =B12-C12 | E12: =IF(B12=0,0,C12/B12)
A13: Репетиция | B13: =COUNTIF('Чек-лист'!$D$5:$D$67,A13) | C13: =COUNTIFS('Чек-лист'!$D$5:$D$67,A13,'Чек-лист'!$B$5:$B$67,"☑") | D13: =B13-C13 | E13: =IF(B13=0,0,C13/B13)
A14: Группа | B14: =COUNTIF('Чек-лист'!$D$5:$D$67,A14) | C14: =COUNTIFS('Чек-лист'!$D$5:$D$67,A14,'Чек-лист'!$B$5:$B$67,"☑") | D14: =B14-C14 | E14: =IF(B14=0,0,C14/B14)
A15: Наблюдение | B15: =COUNTIF('Чек-лист'!$D$5:$D$67,A15) | C15: =COUNTIFS('Чек-лист'!$D$5:$D$67,A15,'Чек-лист'!$B$5:$B$67,"☑") | D15: =B15-C15 | E15: =IF(B15=0,0,C15/B15)
... A18: Итоги | B18: =COUNTIF('Чек-лист'!$D$5:$D$67,A18) | C18: =COUNTIFS('Чек-лист'!$D$5:$D$67,A18,'Чек-лист'!$B$5:$B$67,"☑") | D18: =B18-C18 | E18: =IF(B18=0,0,C18/B18)
A19: Итого | B19: =SUM(B4:B18) | C19: =SUM(C4:C18) | D19: =SUM(D4:D18) | E19: =IF(B19=0,0,C19/B19)
A21: Считается автоматически по столбцам «Блок» и «Готово» листа «Чек-лист».
